reddit_edgecontext/__init__.py
reddit_edgecontext/py.typed
reddit_edgecontext/thrift/__init__.py
reddit_edgecontext/thrift/constants.py
reddit_edgecontext/thrift/ttypes.py
reddit_edgecontext-1.10.0.dist-info/METADATA
reddit_edgecontext-1.10.0.dist-info/WHEEL
reddit_edgecontext-1.10.0.dist-info/top_level.txt
reddit_edgecontext-1.10.0.dist-info/zip-safe
reddit_edgecontext-1.10.0.dist-info/RECORD
