Metadata-Version: 2.1
Name: reddit_edgecontext
Version: 1.10.0
Summary: reddit edge request context baggage
Home-page: https://github.com/reddit/edgecontext
Author: reddit
License: BSD
Project-URL: Documentation, https://reddit-edgecontext.readthedocs.io/
Classifier: Development Status :: 5 - Production/Stable
Classifier: License :: OSI Approved :: BSD License
Classifier: Operating System :: POSIX :: Linux
Classifier: Programming Language :: Python
Classifier: Programming Language :: Python :: 3.7
Classifier: Programming Language :: Python :: 3.8
Classifier: Topic :: Software Development :: Libraries
Requires-Python: >=3.9
Requires-Dist: baseplate <3.0,>=1.5
Requires-Dist: pyjwt <3.0,>=2.0.0
Requires-Dist: thrift <1.0,>=0.14
Requires-Dist: cryptography >=3.0
